intaqt/__init__.py
intaqt/api.py
Intaqt-0.0.6.dist-info/LICENSE
Intaqt-0.0.6.dist-info/METADATA
Intaqt-0.0.6.dist-info/WHEEL
Intaqt-0.0.6.dist-info/top_level.txt
Intaqt-0.0.6.dist-info/RECORD
