Metadata-Version: 2.1
Name: Intaqt
Version: 0.0.6
Summary: Status tracking API
Author-email: Binary Ink Studio <contact@binaryinkstudio.com>
License: Copyright (c) 2022 The Python Packaging Authority        
Project-URL: Homepage, https://www.binaryinkstudio.com
Project-URL: Bug Tracker, https://www.binaryinkstudio.com
Classifier: Programming Language :: Python :: 3
Classifier: License :: OSI Approved :: MIT License
Classifier: Operating System :: OS Independent
Requires-Python: >=3.7
License-File: LICENSE
Requires-Dist: requests
